YitianXuexiYigeNpmLunziFix1/README.md
YitianXuexiYigeNpmLunziFix1/__init__.py
YitianXuexiYigeNpmLunziFix1/__main__.py
YitianXuexiYigeNpmLunziFix1/file.epub
YitianXuexiYigeNpmLunziFix1/index.html
YitianXuexiYigeNpmLunziFix1/css/__init__.py
YitianXuexiYigeNpmLunziFix1/css/annotations.css
YitianXuexiYigeNpmLunziFix1/css/main.css
YitianXuexiYigeNpmLunziFix1/css/normalize.css
YitianXuexiYigeNpmLunziFix1/css/popup.css
YitianXuexiYigeNpmLunziFix1/font/__init__.py
YitianXuexiYigeNpmLunziFix1/font/fontello.eot
YitianXuexiYigeNpmLunziFix1/font/fontello.svg
YitianXuexiYigeNpmLunziFix1/font/fontello.ttf
YitianXuexiYigeNpmLunziFix1/font/fontello.woff
YitianXuexiYigeNpmLunziFix1/img/__init__.py
YitianXuexiYigeNpmLunziFix1/img/annotator-glyph-sprite.png
YitianXuexiYigeNpmLunziFix1/img/annotator-icon-sprite.png
YitianXuexiYigeNpmLunziFix1/img/apple-touch-icon.png
YitianXuexiYigeNpmLunziFix1/img/cancelfullscreen.png
YitianXuexiYigeNpmLunziFix1/img/close.png
YitianXuexiYigeNpmLunziFix1/img/fullscreen.png
YitianXuexiYigeNpmLunziFix1/img/loader.gif
YitianXuexiYigeNpmLunziFix1/img/menu-icon.png
YitianXuexiYigeNpmLunziFix1/img/save.png
YitianXuexiYigeNpmLunziFix1/img/saved.png
YitianXuexiYigeNpmLunziFix1/img/settings-s.png
YitianXuexiYigeNpmLunziFix1/img/settings.png
YitianXuexiYigeNpmLunziFix1/img/star.png
YitianXuexiYigeNpmLunziFix1/js/__init__.py
YitianXuexiYigeNpmLunziFix1/js/epub.js
YitianXuexiYigeNpmLunziFix1/js/epub.min.js
YitianXuexiYigeNpmLunziFix1/js/epub.min.map
YitianXuexiYigeNpmLunziFix1/js/hooks.min.js
YitianXuexiYigeNpmLunziFix1/js/hooks.min.map
YitianXuexiYigeNpmLunziFix1/js/reader.js
YitianXuexiYigeNpmLunziFix1/js/reader.js.map
YitianXuexiYigeNpmLunziFix1/js/reader.min.js
YitianXuexiYigeNpmLunziFix1/js/reader.min.map
YitianXuexiYigeNpmLunziFix1/js/hooks/__init__.py
YitianXuexiYigeNpmLunziFix1/js/hooks/extensions/__init__.py
YitianXuexiYigeNpmLunziFix1/js/hooks/extensions/highlight.js
YitianXuexiYigeNpmLunziFix1/js/libs/__init__.py
yitian_xuexi_yige_npm_lunzi_fix1-2025.3.25.0.dist-info/METADATA
yitian_xuexi_yige_npm_lunzi_fix1-2025.3.25.0.dist-info/WHEEL
yitian_xuexi_yige_npm_lunzi_fix1-2025.3.25.0.dist-info/entry_points.txt
yitian_xuexi_yige_npm_lunzi_fix1-2025.3.25.0.dist-info/top_level.txt
yitian_xuexi_yige_npm_lunzi_fix1-2025.3.25.0.dist-info/RECORD
